mc_post-0.1.4.dist-info/licenses/LICENSE
mcpost/__init__.py
mcpost/_version.py
mcpost/py.typed
mcpost/gsa/__init__.py
mcpost/gsa/base.py
mcpost/gsa/chunked_pipeline.py
mcpost/gsa/kernels.py
mcpost/gsa/metrics.py
mcpost/gsa/pipeline.py
mcpost/gsa/plotting.py
mcpost/integration/__init__.py
mcpost/integration/base.py
mcpost/integration/chunked_integration.py
mcpost/integration/importance.py
mcpost/integration/monte_carlo.py
mcpost/integration/quasi_monte_carlo.py
mcpost/utils/__init__.py
mcpost/utils/chunked.py
mcpost/utils/config.py
mcpost/utils/data.py
mcpost/utils/profiling.py
mcpost/utils/validation.py
mc_post-0.1.4.dist-info/METADATA
mc_post-0.1.4.dist-info/WHEEL
mc_post-0.1.4.dist-info/top_level.txt
mc_post-0.1.4.dist-info/RECORD
