Metadata-Version: 2.4
Name: MC-post
Version: 0.1.4
Summary: Monte Carlo Post-analysis package for global sensitivity analysis and integration
Author-email: MCPost Contributors <mcpost@example.com>
Maintainer-email: MCPost Contributors <mcpost@example.com>
License-Expression: MIT
Project-URL: Homepage, https://github.com/zzhang0123/mcpost
Project-URL: Repository, https://github.com/zzhang0123/mcpost
Project-URL: Bug Tracker, https://github.com/zzhang0123/mcpost/issues
Keywords: monte-carlo,sensitivity-analysis,integration,statistics
Classifier: Development Status :: 4 - Beta
Classifier: Intended Audience :: Science/Research
Classifier: Operating System :: OS Independent
Classifier: Programming Language :: Python :: 3
Classifier: Programming Language :: Python :: 3.8
Classifier: Programming Language :: Python :: 3.9
Classifier: Programming Language :: Python :: 3.10
Classifier: Programming Language :: Python :: 3.11
Classifier: Topic :: Scientific/Engineering
Classifier: Topic :: Scientific/Engineering :: Mathematics
Requires-Python: >=3.8
License-File: LICENSE
Requires-Dist: numpy<2.4.0,>=1.20.0
Requires-Dist: pandas>=1.3.0
Requires-Dist: scikit-learn>=1.0.0
Requires-Dist: scipy>=1.7.0
Requires-Dist: dcor>=0.5.0
Requires-Dist: SALib>=1.4.0
Requires-Dist: tqdm>=4.60.0
Requires-Dist: psutil>=5.8.0
Provides-Extra: viz
Requires-Dist: matplotlib>=3.5.0; extra == "viz"
Provides-Extra: jupyter
Requires-Dist: jupyter>=1.0.0; extra == "jupyter"
Requires-Dist: notebook>=6.4.0; extra == "jupyter"
Requires-Dist: ipykernel>=6.0.0; extra == "jupyter"
Provides-Extra: dev
Requires-Dist: pytest>=6.0; extra == "dev"
Requires-Dist: pytest-cov>=3.0; extra == "dev"
Requires-Dist: hypothesis>=6.0; extra == "dev"
Requires-Dist: black>=22.0; extra == "dev"
Requires-Dist: flake8>=4.0; extra == "dev"
Requires-Dist: mypy>=0.900; extra == "dev"
Requires-Dist: build>=0.8.0; extra == "dev"
Requires-Dist: twine>=4.0.0; extra == "dev"
Requires-Dist: isort>=5.10.0; extra == "dev"
Requires-Dist: safety>=2.0.0; extra == "dev"
Requires-Dist: bandit>=1.7.0; extra == "dev"
Requires-Dist: radon>=5.1.0; extra == "dev"
Requires-Dist: xenon>=0.9.0; extra == "dev"
Requires-Dist: docstr-coverage>=2.0.0; extra == "dev"
Requires-Dist: pip-audit>=2.0.0; extra == "dev"
Provides-Extra: docs
Requires-Dist: sphinx>=4.0; extra == "docs"
Requires-Dist: sphinx-rtd-theme>=1.0; extra == "docs"
Requires-Dist: jupyter>=1.0; extra == "docs"
Requires-Dist: nbsphinx>=0.8; extra == "docs"
Requires-Dist: nbconvert>=6.0; extra == "docs"
Requires-Dist: readme-renderer>=35.0; extra == "docs"
Provides-Extra: all
Requires-Dist: mcpost[dev,docs,jupyter,viz]; extra == "all"
Dynamic: license-file
